<annotation>
	<folder>GF2_PMS1_E113.4_N23.3_20170915_L1A0002600401-</folder>
	<filename>GF2_PMS1_E113.4_N23.3_20170915_L1A0002600401-15.png</filename>
	<path>D:\遥感影像\task\image\0\GF2_PMS1_E113.4_N23.3_20170915_L1A0002600401-\GF2_PMS1_E113.4_N23.3_20170915_L1A0002600401-15.png</path>
	<source>
		<database>Unknown</database>
	</source>
	<size>
		<width>1024</width>
		<height>1024</height>
		<depth>3</depth>
	</size>
	<segmented>0</segmented>
	<object>
		<name>plane</name>
		<pose>Unspecified</pose>
		<truncated>0</truncated>
		<difficult>0</difficult>
		<bndbox>
			<xmin>623</xmin>
			<ymin>24</ymin>
			<xmax>642</xmax>
			<ymax>44</ymax>
		</bndbox>
	</object>
	<object>
		<name>plane</name>
		<pose>Unspecified</pose>
		<truncated>0</truncated>
		<difficult>0</difficult>
		<bndbox>
			<xmin>617</xmin>
			<ymin>58</ymin>
			<xmax>637</xmax>
			<ymax>78</ymax>
		</bndbox>
	</object>
	<object>
		<name>plane</name>
		<pose>Unspecified</pose>
		<truncated>0</truncated>
		<difficult>0</difficult>
		<bndbox>
			<xmin>986</xmin>
			<ymin>61</ymin>
			<xmax>1006</xmax>
			<ymax>92</ymax>
		</bndbox>
	</object>
	<object>
		<name>plane</name>
		<pose>Unspecified</pose>
		<truncated>0</truncated>
		<difficult>0</difficult>
		<bndbox>
			<xmin>939</xmin>
			<ymin>48</ymin>
			<xmax>960</xmax>
			<ymax>74</ymax>
		</bndbox>
	</object>
	<object>
		<name>plane</name>
		<pose>Unspecified</pose>
		<truncated>0</truncated>
		<difficult>0</difficult>
		<bndbox>
			<xmin>994</xmin>
			<ymin>145</ymin>
			<xmax>1021</xmax>
			<ymax>166</ymax>
		</bndbox>
	</object>
</annotation>
